egse/plugins/storage/hdf5.py
plato_hdf5-2025.0.9.dist-info/METADATA
plato_hdf5-2025.0.9.dist-info/WHEEL
plato_hdf5-2025.0.9.dist-info/entry_points.txt
plato_hdf5-2025.0.9.dist-info/RECORD
