Metadata-Version: 2.4
Name: plato-hdf5
Version: 2025.0.9
Summary: HDF5 Persistence sub-class for CGSE
Author: IVS KU Leuven
Maintainer-email: Rik Huygen <rik.huygen@kuleuven.be>, Sara Regibo <sara.regibo@kuleuven.be>
License-Expression: MIT
Keywords: CGSE,Common-EGSE,hardware testing,software framework
Requires-Python: >=3.9
Requires-Dist: cgse-common
Requires-Dist: h5py>=3.12.1
Requires-Dist: natsort>=8.4.0
Requires-Dist: plato-spw
Provides-Extra: test
Requires-Dist: pytest; extra == 'test'
Requires-Dist: pytest-cov; extra == 'test'
Requires-Dist: pytest-mock; extra == 'test'
